setup.py
rube_mc_pi/__init__.py
rube_mc_pi/demo_http_server.py
rube_mc_pi/file.py
rube_mc_pi/firmata.py
rube_mc_pi/gpio.py
rube_mc_pi/http.py
rube_mc_pi/minecraft.py
rube_mc_pi/mock.py
rube_mc_pi/mock2.py
rube_mc_pi/playerloc.py
rube_mc_pi/rube.py
rube_mc_pi/scratchplug.py
rube_mc_pi/twilioplug.py
rube_mc_pi.egg-info/PKG-INFO
rube_mc_pi.egg-info/SOURCES.txt
rube_mc_pi.egg-info/dependency_links.txt
rube_mc_pi.egg-info/not-zip-safe
rube_mc_pi.egg-info/requires.txt
rube_mc_pi.egg-info/top_level.txt
rube_mc_pi/mcpi/__init__.py
rube_mc_pi/mcpi/block.py
rube_mc_pi/mcpi/connection.py
rube_mc_pi/mcpi/event.py
rube_mc_pi/mcpi/minecraft.py
rube_mc_pi/mcpi/util.py
rube_mc_pi/mcpi/vec3.py