Metadata-Version: 1.0
Name: rube-mc-pi
Version: 0.2.1
Summary: Controller code for the Manchester CoderDojo Rube Goldberg Proejct
Home-page: https://github.com/davegoopot/rube-mc-pi
Author: Dave Potts
Author-email: dave@goopot.co.uk
License: GPL2
Platform: UNKNOWN
